Classfile /Users/libo/IdeaProjects/demo/jvm/src/TulingByteCode2.class
  Last modified 2020-6-10; size 532 bytes
  MD5 checksum e7d594ed38ad57bc7b2b25144a08a11b
  Compiled from "TulingByteCode2.java"
public class TulingByteCode2
  minor version: 0
  major version: 52
  flags: ACC_PUBLIC, ACC_SUPER
Constant pool:
   #1 = Methodref          #4.#20         // java/lang/Object."<init>":()V
   #2 = Fieldref           #3.#21         // TulingByteCode2.userName:Ljava/lang/String;
   #3 = Class              #22            // TulingByteCode2
   #4 = Class              #23            // java/lang/Object
   #5 = Utf8               userName
   #6 = Utf8               Ljava/lang/String;
   #7 = Utf8               <init>
   #8 = Utf8               ()V
   #9 = Utf8               Code
  #10 = Utf8               LineNumberTable
  #11 = Utf8               LocalVariableTable
  #12 = Utf8               this
  #13 = Utf8               LTulingByteCode2;
  #14 = Utf8               getUserName
  #15 = Utf8               ()Ljava/lang/String;
  #16 = Utf8               setUserName
  #17 = Utf8               (Ljava/lang/String;)V
  #18 = Utf8               SourceFile
  #19 = Utf8               TulingByteCode2.java
  #20 = NameAndType        #7:#8          // "<init>":()V
  #21 = NameAndType        #5:#6          // userName:Ljava/lang/String;
  #22 = Utf8               TulingByteCode2
  #23 = Utf8               java/lang/Object
{
  public TulingByteCode2();
    descriptor: ()V
    flags: ACC_PUBLIC
    Code:
      stack=1, locals=1, args_size=1
         0: aload_0
         1: invokespecial #1                  // Method java/lang/Object."<init>":()V
         4: return
      LineNumberTable:
        line 5: 0
      LocalVariableTable:
        Start  Length  Slot  Name   Signature
            0       5     0  this   LTulingByteCode2;

  public java.lang.String getUserName();
    descriptor: ()Ljava/lang/String;
    flags: ACC_PUBLIC
    Code:
      stack=1, locals=1, args_size=1
         0: aload_0
         1: getfield      #2                  // Field userName:Ljava/lang/String;
         4: areturn
      LineNumberTable:
        line 10: 0
      LocalVariableTable:
        Start  Length  Slot  Name   Signature
            0       5     0  this   LTulingByteCode2;

  public void setUserName(java.lang.String);
    descriptor: (Ljava/lang/String;)V
    flags: ACC_PUBLIC
    Code:
      stack=2, locals=2, args_size=2
         0: aload_0
         1: aload_1
         2: putfield      #2                  // Field userName:Ljava/lang/String;
         5: return
      LineNumberTable:
        line 14: 0
        line 15: 5
      LocalVariableTable:
        Start  Length  Slot  Name   Signature
            0       6     0  this   LTulingByteCode2;
            0       6     1 userName   Ljava/lang/String;
}
SourceFile: "TulingByteCode2.java"
